{"timestamp": 1716263340, "x": 24.6130094637224, "y": 8.156697160883281, "MAC1_range": 0, "MAC1_rssi": -100, "MAC2_range": 10450.0, "MAC2_rssi": -79.70314529, "MAC3_range": 0, "MAC3_rssi": -100, "MAC4_range": 0, "MAC4_rssi": -100, "MAC5_range": 0, "MAC5_rssi": -100, "MAC6_range": 12580.0, "MAC6_rssi": -79.04276964, "MAC7_range": 0, "MAC7_rssi": -100, "MAC8_range": 0, "MAC8_rssi": -100, "MAC9_range": 0, "MAC9_rssi": -100, "MAC10_range": 3190.0, "MAC10_rssi": -75.83046765, "MAC11_range": 10990.0, "MAC11_rssi": -79.16897667, "MAC12_range": 0, "MAC12_rssi": -100, "MAC13_range": 0, "MAC13_rssi": -100, "MAC14_range": 0, "MAC14_rssi": -100}
{"timestamp": 1716263340, "x": 24.6130094637224, "y": 8.156697160883281, "MAC1_range": 0, "MAC1_rssi": -100, "MAC2_range": 10440.0, "MAC2_rssi": -79.50530019, "MAC3_range": 0, "MAC3_rssi": -100, "MAC4_range": 0, "MAC4_rssi": -100, "MAC5_range": 0, "MAC5_rssi": -100, "MAC6_range": 12830.0, "MAC6_rssi": -78.50479772, "MAC7_range": 0, "MAC7_rssi": -100, "MAC8_range": 0, "MAC8_rssi": -100, "MAC9_range": 0, "MAC9_rssi": -100, "MAC10_range": 3250.0, "MAC10_rssi": -75.96922011, "MAC11_range": 11000.0, "MAC11_rssi": -79.19451923, "MAC12_range": 0, "MAC12_rssi": -100, "MAC13_range": 0, "MAC13_rssi": -100, "MAC14_range": 0, "MAC14_rssi": -100}
{"timestamp": 1716263341, "x": 24.6130094637224, "y": 8.156697160883281, "MAC1_range": 0, "MAC1_rssi": -100, "MAC2_range": 0, "MAC2_rssi": -100, "MAC3_range": 0, "MAC3_rssi": -100, "MAC4_range": 7910.0, "MAC4_rssi": -75.44254106, "MAC5_range": 11480.0, "MAC5_rssi": -79.16225459, "MAC6_range": 0, "MAC6_rssi": -100, "MAC7_range": 0, "MAC7_rssi": -100, "MAC8_range": 0, "MAC8_rssi": -100, "MAC9_range": 6430.0, "MAC9_rssi": -75.67543392, "MAC10_range": 3210.0, "MAC10_rssi": -75.79729025, "MAC11_range": 0, "MAC11_rssi": -100, "MAC12_range": 0, "MAC12_rssi": -100, "MAC13_range": 0, "MAC13_rssi": -100, "MAC14_range": 3170.0, "MAC14_rssi": -76.21149346}
{"timestamp": 1716263341, "x": 24.6130094637224, "y": 8.156697160883281, "MAC1_range": 0, "MAC1_rssi": -100, "MAC2_range": 0, "MAC2_rssi": -100, "MAC3_range": 0, "MAC3_rssi": -100, "MAC4_range": 7890.0, "MAC4_rssi": -75.70768994, "MAC5_range": 11490.0, "MAC5_rssi": -79.18028361, "MAC6_range": 0, "MAC6_rssi": -100, "MAC7_range": 0, "MAC7_rssi": -100, "MAC8_range": 0, "MAC8_rssi": -100, "MAC9_range": 6390.0, "MAC9_rssi": -75.5357243, "MAC10_range": 3200.0, "MAC10_rssi": -75.9932067, "MAC11_range": 0, "MAC11_rssi": -100, "MAC12_range": 0, "MAC12_rssi": -100, "MAC13_range": 0, "MAC13_rssi": -100, "MAC14_range": 3270.0, "MAC14_rssi": -76.3348283}
{"timestamp": 1716263342, "x": 24.6130094637224, "y": 8.156697160883281, "MAC1_range": 0, "MAC1_rssi": -100, "MAC2_range": 0, "MAC2_rssi": -100, "MAC3_range": 0, "MAC3_rssi": -100, "MAC4_range": 7870.0, "MAC4_rssi": -75.47844478, "MAC5_range": 11500.0, "MAC5_rssi": -79.29896137, "MAC6_range": 12910.0, "MAC6_rssi": -78.23674436, "MAC7_range": 0, "MAC7_rssi": -100, "MAC8_range": 0, "MAC8_rssi": -100, "MAC9_range": 7670.0, "MAC9_rssi": -75.46705849, "MAC10_range": 3230.0, "MAC10_rssi": -75.8381601, "MAC11_range": 11010.0, "MAC11_rssi": -78.77861547, "MAC12_range": 0, "MAC12_rssi": -100, "MAC13_range": 0, "MAC13_rssi": -100, "MAC14_range": 3230.0, "MAC14_rssi": -75.98511949}
{"timestamp": 1716263342, "x": 24.6130094637224, "y": 8.156697160883281, "MAC1_range": 0, "MAC1_rssi": -100, "MAC2_range": 0, "MAC2_rssi": -100, "MAC3_range": 0, "MAC3_rssi": -100, "MAC4_range": 7870.0, "MAC4_rssi": -75.47844478, "MAC5_range": 11500.0, "MAC5_rssi": -79.29896137, "MAC6_range": 12910.0, "MAC6_rssi": -78.23674436, "MAC7_range": 0, "MAC7_rssi": -100, "MAC8_range": 0, "MAC8_rssi": -100, "MAC9_range": 7670.0, "MAC9_rssi": -75.46705849, "MAC10_range": 3230.0, "MAC10_rssi": -75.8381601, "MAC11_range": 11010.0, "MAC11_rssi": -78.77861547, "MAC12_range": 0, "MAC12_rssi": -100, "MAC13_range": 0, "MAC13_rssi": -100, "MAC14_range": 3230.0, "MAC14_rssi": -75.98511949}
{"timestamp": 1716263343, "x": 24.6130094637224, "y": 8.156697160883281, "MAC1_range": 0, "MAC1_rssi": -100, "MAC2_range": 10480.0, "MAC2_rssi": -79.59447545, "MAC3_range": 0, "MAC3_rssi": -100, "MAC4_range": 0, "MAC4_rssi": -100, "MAC5_range": 0, "MAC5_rssi": -100, "MAC6_range": 12900.0, "MAC6_rssi": -78.77422555, "MAC7_range": 0, "MAC7_rssi": -100, "MAC8_range": 0, "MAC8_rssi": -100, "MAC9_range": 0, "MAC9_rssi": -100, "MAC10_range": 3230.0, "MAC10_rssi": -75.81312608, "MAC11_range": 10970.0, "MAC11_rssi": -79.35226498, "MAC12_range": 0, "MAC12_rssi": -100, "MAC13_range": 0, "MAC13_rssi": -100, "MAC14_range": 0, "MAC14_rssi": -100}
{"timestamp": 1716263343, "x": 24.6130094637224, "y": 8.156697160883281, "MAC1_range": 0, "MAC1_rssi": -100, "MAC2_range": 10440.0, "MAC2_rssi": -79.76554028, "MAC3_range": 0, "MAC3_rssi": -100, "MAC4_range": 0, "MAC4_rssi": -100, "MAC5_range": 0, "MAC5_rssi": -100, "MAC6_range": 9120.0, "MAC6_rssi": -79.14668975, "MAC7_range": 0, "MAC7_rssi": -100, "MAC8_range": 0, "MAC8_rssi": -100, "MAC9_range": 0, "MAC9_rssi": -100, "MAC10_range": 3150.0, "MAC10_rssi": -75.86457399, "MAC11_range": 10990.0, "MAC11_rssi": -79.52168623, "MAC12_range": 0, "MAC12_rssi": -100, "MAC13_range": 0, "MAC13_rssi": -100, "MAC14_range": 0, "MAC14_rssi": -100}
{"timestamp": 1716263344, "x": 24.6130094637224, "y": 8.156697160883281, "MAC1_range": 0, "MAC1_rssi": -100, "MAC2_range": 10420.0, "MAC2_rssi": -79.38269603, "MAC3_range": 0, "MAC3_rssi": -100, "MAC4_range": 7960.0, "MAC4_rssi": -75.48996399, "MAC5_range": 11330.0, "MAC5_rssi": -79.18558635, "MAC6_range": 12630.0, "MAC6_rssi": -78.53749828, "MAC7_range": 0, "MAC7_rssi": -100, "MAC8_range": 0, "MAC8_rssi": -100, "MAC9_range": 6530.0, "MAC9_rssi": -75.56632657, "MAC10_range": 3210.0, "MAC10_rssi": -75.83525989, "MAC11_range": 11030.0, "MAC11_rssi": -78.8134527, "MAC12_range": 0, "MAC12_rssi": -100, "MAC13_range": 0, "MAC13_rssi": -100, "MAC14_range": 3260.0, "MAC14_rssi": -76.19910793}
{"timestamp": 1716263344, "x": 24.6130094637224, "y": 8.156697160883281, "MAC1_range": 0, "MAC1_rssi": -100, "MAC2_range": 10420.0, "MAC2_rssi": -79.39103254, "MAC3_range": 0, "MAC3_rssi": -100, "MAC4_range": 7930.0, "MAC4_rssi": -75.66759496, "MAC5_range": 11400.0, "MAC5_rssi": -79.33700418, "MAC6_range": 12630.0, "MAC6_rssi": -78.53749828, "MAC7_range": 0, "MAC7_rssi": -100, "MAC8_range": 0, "MAC8_rssi": -100, "MAC9_range": 6400.0, "MAC9_rssi": -75.49315775, "MAC10_range": 3200.0, "MAC10_rssi": -75.83916447, "MAC11_range": 10970.0, "MAC11_rssi": -78.83497939, "MAC12_range": 0, "MAC12_rssi": -100, "MAC13_range": 0, "MAC13_rssi": -100, "MAC14_range": 3230.0, "MAC14_rssi": -76.13137305}
{"timestamp": 1716263345, "x": 24.6130094637224, "y": 8.156697160883281, "MAC1_range": 0, "MAC1_rssi": -100, "MAC2_range": 10460.0, "MAC2_rssi": -79.25193296, "MAC3_range": 0, "MAC3_rssi": -100, "MAC4_range": 0, "MAC4_rssi": -100, "MAC5_range": 0, "MAC5_rssi": -100, "MAC6_range": 12880.0, "MAC6_rssi": -78.86982499, "MAC7_range": 0, "MAC7_rssi": -100, "MAC8_range": 0, "MAC8_rssi": -100, "MAC9_range": 0, "MAC9_rssi": -100, "MAC10_range": 3180.0, "MAC10_rssi": -76.01151623, "MAC11_range": 11010.0, "MAC11_rssi": -78.97952007, "MAC12_range": 0, "MAC12_rssi": -100, "MAC13_range": 0, "MAC13_rssi": -100, "MAC14_range": 0, "MAC14_rssi": -100}
{"timestamp": 1716263345, "x": 24.6130094637224, "y": 8.156697160883281, "MAC1_range": 0, "MAC1_rssi": -100, "MAC2_range": 10480.0, "MAC2_rssi": -79.274768, "MAC3_range": 0, "MAC3_rssi": -100, "MAC4_range": 0, "MAC4_rssi": -100, "MAC5_range": 0, "MAC5_rssi": -100, "MAC6_range": 12930.0, "MAC6_rssi": -78.53355289, "MAC7_range": 0, "MAC7_rssi": -100, "MAC8_range": 0, "MAC8_rssi": -100, "MAC9_range": 0, "MAC9_rssi": -100, "MAC10_range": 3260.0, "MAC10_rssi": -75.75888267, "MAC11_range": 10980.0, "MAC11_rssi": -79.13213331, "MAC12_range": 0, "MAC12_rssi": -100, "MAC13_range": 0, "MAC13_rssi": -100, "MAC14_range": 0, "MAC14_rssi": -100}
{"timestamp": 1716263346, "x": 24.6130094637224, "y": 8.156697160883281, "MAC1_range": 0, "MAC1_rssi": -100, "MAC2_range": 11280.0, "MAC2_rssi": -79.23702008, "MAC3_range": 0, "MAC3_rssi": -100, "MAC4_range": 7900.0, "MAC4_rssi": -75.79850634, "MAC5_range": 11000.0, "MAC5_rssi": -78.94378678, "MAC6_range": 11140.0, "MAC6_rssi": -78.54914771, "MAC7_range": 0, "MAC7_rssi": -100, "MAC8_range": 0, "MAC8_rssi": -100, "MAC9_range": 7670.0, "MAC9_rssi": -75.55951903, "MAC10_range": 3250.0, "MAC10_rssi": -75.72016017, "MAC11_range": 10970.0, "MAC11_rssi": -78.40290817, "MAC12_range": 0, "MAC12_rssi": -100, "MAC13_range": 0, "MAC13_rssi": -100, "MAC14_range": 3210.0, "MAC14_rssi": -75.90098759}
{"timestamp": 1716263346, "x": 24.6130094637224, "y": 8.156697160883281, "MAC1_range": 0, "MAC1_rssi": -100, "MAC2_range": 11280.0, "MAC2_rssi": -79.15793874, "MAC3_range": 0, "MAC3_rssi": -100, "MAC4_range": 7900.0, "MAC4_rssi": -75.79850634, "MAC5_range": 11000.0, "MAC5_rssi": -78.94378678, "MAC6_range": 11400.0, "MAC6_rssi": -78.3924476, "MAC7_range": 0, "MAC7_rssi": -100, "MAC8_range": 0, "MAC8_rssi": -100, "MAC9_range": 7670.0, "MAC9_rssi": -75.55951903, "MAC10_range": 3250.0, "MAC10_rssi": -75.72016017, "MAC11_range": 10960.0, "MAC11_rssi": -79.33650473, "MAC12_range": 0, "MAC12_rssi": -100, "MAC13_range": 0, "MAC13_rssi": -100, "MAC14_range": 3210.0, "MAC14_rssi": -75.90098759}
{"timestamp": 1716263347, "x": 24.6130094637224, "y": 8.156697160883281, "MAC1_range": 0, "MAC1_rssi": -100, "MAC2_range": 10450.0, "MAC2_rssi": -79.67957099, "MAC3_range": 0, "MAC3_rssi": -100, "MAC4_range": 7910.0, "MAC4_rssi": -75.65902054, "MAC5_range": 11390.0, "MAC5_rssi": -78.81766087, "MAC6_range": 9840.0, "MAC6_rssi": -78.37980788, "MAC7_range": 0, "MAC7_rssi": -100, "MAC8_range": 0, "MAC8_rssi": -100, "MAC9_range": 6470.0, "MAC9_rssi": -75.56789905, "MAC10_range": 3260.0, "MAC10_rssi": -75.54750101, "MAC11_range": 11040.0, "MAC11_rssi": -79.10032716, "MAC12_range": 0, "MAC12_rssi": -100, "MAC13_range": 0, "MAC13_rssi": -100, "MAC14_range": 3170.0, "MAC14_rssi": -75.64811264}
{"timestamp": 1716263347, "x": 24.6130094637224, "y": 8.156697160883281, "MAC1_range": 0, "MAC1_rssi": -100, "MAC2_range": 10450.0, "MAC2_rssi": -79.67957099, "MAC3_range": 0, "MAC3_rssi": -100, "MAC4_range": 7930.0, "MAC4_rssi": -75.93097823, "MAC5_range": 11450.0, "MAC5_rssi": -79.03111635, "MAC6_range": 9840.0, "MAC6_rssi": -78.37980788, "MAC7_range": 0, "MAC7_rssi": -100, "MAC8_range": 0, "MAC8_rssi": -100, "MAC9_range": 6500.0, "MAC9_rssi": -75.57062605, "MAC10_range": 3310.0, "MAC10_rssi": -75.53749398, "MAC11_range": 11040.0, "MAC11_rssi": -79.10032716, "MAC12_range": 0, "MAC12_rssi": -100, "MAC13_range": 0, "MAC13_rssi": -100, "MAC14_range": 3230.0, "MAC14_rssi": -75.72842106}
{"timestamp": 1716263348, "x": 24.6130094637224, "y": 8.156697160883281, "MAC1_range": 0, "MAC1_rssi": -100, "MAC2_range": 10470.0, "MAC2_rssi": -79.24557039, "MAC3_range": 0, "MAC3_rssi": -100, "MAC4_range": 0, "MAC4_rssi": -100, "MAC5_range": 0, "MAC5_rssi": -100, "MAC6_range": 13100.0, "MAC6_rssi": -78.5723313, "MAC7_range": 0, "MAC7_rssi": -100, "MAC8_range": 0, "MAC8_rssi": -100, "MAC9_range": 0, "MAC9_rssi": -100, "MAC10_range": 3320.0, "MAC10_rssi": -75.57450972, "MAC11_range": 10960.0, "MAC11_rssi": -79.0051259, "MAC12_range": 0, "MAC12_rssi": -100, "MAC13_range": 0, "MAC13_rssi": -100, "MAC14_range": 0, "MAC14_rssi": -100}
{"timestamp": 1716263348, "x": 24.6130094637224, "y": 8.156697160883281, "MAC1_range": 0, "MAC1_rssi": -100, "MAC2_range": 10470.0, "MAC2_rssi": -79.24557039, "MAC3_range": 0, "MAC3_rssi": -100, "MAC4_range": 0, "MAC4_rssi": -100, "MAC5_range": 0, "MAC5_rssi": -100, "MAC6_range": 13100.0, "MAC6_rssi": -78.5723313, "MAC7_range": 0, "MAC7_rssi": -100, "MAC8_range": 0, "MAC8_rssi": -100, "MAC9_range": 0, "MAC9_rssi": -100, "MAC10_range": 3280.0, "MAC10_rssi": -75.61767305, "MAC11_range": 10980.0, "MAC11_rssi": -79.19234468, "MAC12_range": 0, "MAC12_rssi": -100, "MAC13_range": 0, "MAC13_rssi": -100, "MAC14_range": 0, "MAC14_rssi": -100}
{"timestamp": 1716263349, "x": 24.6130094637224, "y": 8.156697160883281, "MAC1_range": 0, "MAC1_rssi": -100, "MAC2_range": 10470.0, "MAC2_rssi": -79.31110878, "MAC3_range": 0, "MAC3_rssi": -100, "MAC4_range": 0, "MAC4_rssi": -100, "MAC5_range": 0, "MAC5_rssi": -100, "MAC6_range": 12730.0, "MAC6_rssi": -78.12857912, "MAC7_range": 0, "MAC7_rssi": -100, "MAC8_range": 0, "MAC8_rssi": -100, "MAC9_range": 0, "MAC9_rssi": -100, "MAC10_range": 3220.0, "MAC10_rssi": -75.56559294, "MAC11_range": 11000.0, "MAC11_rssi": -78.8873532, "MAC12_range": 0, "MAC12_rssi": -100, "MAC13_range": 0, "MAC13_rssi": -100, "MAC14_range": 0, "MAC14_rssi": -100}
{"timestamp": 1716263349, "x": 24.6130094637224, "y": 8.156697160883281, "MAC1_range": 0, "MAC1_rssi": -100, "MAC2_range": 10450.0, "MAC2_rssi": -79.16057569, "MAC3_range": 0, "MAC3_rssi": -100, "MAC4_range": 0, "MAC4_rssi": -100, "MAC5_range": 0, "MAC5_rssi": -100, "MAC6_range": 12820.0, "MAC6_rssi": -78.46212092, "MAC7_range": 0, "MAC7_rssi": -100, "MAC8_range": 0, "MAC8_rssi": -100, "MAC9_range": 0, "MAC9_rssi": -100, "MAC10_range": 3180.0, "MAC10_rssi": -75.61905205, "MAC11_range": 11040.0, "MAC11_rssi": -78.72709506, "MAC12_range": 0, "MAC12_rssi": -100, "MAC13_range": 0, "MAC13_rssi": -100, "MAC14_range": 0, "MAC14_rssi": -100}
{"timestamp": 1716263350, "x": 24.6130094637224, "y": 8.156697160883281, "MAC1_range": 0, "MAC1_rssi": -100, "MAC2_range": 10460.0, "MAC2_rssi": -79.23921712, "MAC3_range": 0, "MAC3_rssi": -100, "MAC4_range": 0, "MAC4_rssi": -100, "MAC5_range": 0, "MAC5_rssi": -100, "MAC6_range": 12860.0, "MAC6_rssi": -78.59922008, "MAC7_range": 0, "MAC7_rssi": -100, "MAC8_range": 0, "MAC8_rssi": -100, "MAC9_range": 0, "MAC9_rssi": -100, "MAC10_range": 3160.0, "MAC10_rssi": -75.38737478, "MAC11_range": 11040.0, "MAC11_rssi": -78.80328134, "MAC12_range": 0, "MAC12_rssi": -100, "MAC13_range": 0, "MAC13_rssi": -100, "MAC14_range": 0, "MAC14_rssi": -100}
{"timestamp": 1716263350, "x": 24.6130094637224, "y": 8.156697160883281, "MAC1_range": 0, "MAC1_rssi": -100, "MAC2_range": 10460.0, "MAC2_rssi": -79.3675796, "MAC3_range": 0, "MAC3_rssi": -100, "MAC4_range": 0, "MAC4_rssi": -100, "MAC5_range": 0, "MAC5_rssi": -100, "MAC6_range": 12760.0, "MAC6_rssi": -78.4511096, "MAC7_range": 0, "MAC7_rssi": -100, "MAC8_range": 0, "MAC8_rssi": -100, "MAC9_range": 0, "MAC9_rssi": -100, "MAC10_range": 3150.0, "MAC10_rssi": -75.71636109, "MAC11_range": 10980.0, "MAC11_rssi": -78.88645259, "MAC12_range": 0, "MAC12_rssi": -100, "MAC13_range": 0, "MAC13_rssi": -100, "MAC14_range": 0, "MAC14_rssi": -100}
{"timestamp": 1716263351, "x": 24.6130094637224, "y": 8.156697160883281, "MAC1_range": 0, "MAC1_rssi": -100, "MAC2_range": 10470.0, "MAC2_rssi": -79.71075972, "MAC3_range": 0, "MAC3_rssi": -100, "MAC4_range": 7920.0, "MAC4_rssi": -75.62202369, "MAC5_range": 10330.0, "MAC5_rssi": -79.29129378, "MAC6_range": 13090.0, "MAC6_rssi": -78.99241946, "MAC7_range": 0, "MAC7_rssi": -100, "MAC8_range": 0, "MAC8_rssi": -100, "MAC9_range": 6540.0, "MAC9_rssi": -75.42495353, "MAC10_range": 3180.0, "MAC10_rssi": -75.57104574, "MAC11_range": 11020.0, "MAC11_rssi": -78.67103402, "MAC12_range": 0, "MAC12_rssi": -100, "MAC13_range": 0, "MAC13_rssi": -100, "MAC14_range": 3210.0, "MAC14_rssi": -76.38642576}
{"timestamp": 1716263351, "x": 24.6130094637224, "y": 8.156697160883281, "MAC1_range": 0, "MAC1_rssi": -100, "MAC2_range": 10470.0, "MAC2_rssi": -79.71075972, "MAC3_range": 0, "MAC3_rssi": -100, "MAC4_range": 7880.0, "MAC4_rssi": -75.06771257, "MAC5_range": 10750.0, "MAC5_rssi": -78.42208413, "MAC6_range": 13090.0, "MAC6_rssi": -78.99241946, "MAC7_range": 0, "MAC7_rssi": -100, "MAC8_range": 0, "MAC8_rssi": -100, "MAC9_range": 6490.0, "MAC9_rssi": -75.43633154, "MAC10_range": 3230.0, "MAC10_rssi": -75.91448047, "MAC11_range": 11020.0, "MAC11_rssi": -78.67103402, "MAC12_range": 0, "MAC12_rssi": -100, "MAC13_range": 0, "MAC13_rssi": -100, "MAC14_range": 3240.0, "MAC14_rssi": -75.91255034}
{"timestamp": 1716263352, "x": 24.6130094637224, "y": 8.156697160883281, "MAC1_range": 0, "MAC1_rssi": -100, "MAC2_range": 10900.0, "MAC2_rssi": -80.49919843, "MAC3_range": 0, "MAC3_rssi": -100, "MAC4_range": 7850.0, "MAC4_rssi": -74.88016556, "MAC5_range": 10940.0, "MAC5_rssi": -79.52168623, "MAC6_range": 13260.0, "MAC6_rssi": -79.73204202, "MAC7_range": 0, "MAC7_rssi": -100, "MAC8_range": 0, "MAC8_rssi": -100, "MAC9_range": 6470.0, "MAC9_rssi": -75.37311552, "MAC10_range": 3250.0, "MAC10_rssi": -75.63425001, "MAC11_range": 11030.0, "MAC11_rssi": -79.75287943, "MAC12_range": 0, "MAC12_rssi": -100, "MAC13_range": 0, "MAC13_rssi": -100, "MAC14_range": 3440.0, "MAC14_rssi": -76.29659056}
{"timestamp": 1716263352, "x": 24.6130094637224, "y": 8.156697160883281, "MAC1_range": 0, "MAC1_rssi": -100, "MAC2_range": 11290.0, "MAC2_rssi": -80.36550937, "MAC3_range": 0, "MAC3_rssi": -100, "MAC4_range": 7850.0, "MAC4_rssi": -74.88016556, "MAC5_range": 10940.0, "MAC5_rssi": -79.52168623, "MAC6_range": 15300.0, "MAC6_rssi": -78.98205085, "MAC7_range": 0, "MAC7_rssi": -100, "MAC8_range": 0, "MAC8_rssi": -100, "MAC9_range": 6470.0, "MAC9_rssi": -75.37311552, "MAC10_range": 3350.0, "MAC10_rssi": -75.16103158, "MAC11_range": 10960.0, "MAC11_rssi": -79.69012296, "MAC12_range": 0, "MAC12_rssi": -100, "MAC13_range": 0, "MAC13_rssi": -100, "MAC14_range": 3440.0, "MAC14_rssi": -76.29659056}
{"timestamp": 1716263353, "x": 24.6130094637224, "y": 8.156697160883281, "MAC1_range": 0, "MAC1_rssi": -100, "MAC2_range": 10540.0, "MAC2_rssi": -79.20758946, "MAC3_range": 0, "MAC3_rssi": -100, "MAC4_range": 7870.0, "MAC4_rssi": -75.79397536, "MAC5_range": 10350.0, "MAC5_rssi": -79.16729518, "MAC6_range": 13200.0, "MAC6_rssi": -79.04487056, "MAC7_range": 0, "MAC7_rssi": -100, "MAC8_range": 0, "MAC8_rssi": -100, "MAC9_range": 6590.0, "MAC9_rssi": -75.47865021, "MAC10_range": 3350.0, "MAC10_rssi": -75.2502558, "MAC11_range": 10960.0, "MAC11_rssi": -78.79379483, "MAC12_range": 0, "MAC12_rssi": -100, "MAC13_range": 0, "MAC13_rssi": -100, "MAC14_range": 0, "MAC14_rssi": -100}
{"timestamp": 1716263353, "x": 24.6130094637224, "y": 8.156697160883281, "MAC1_range": 0, "MAC1_rssi": -100, "MAC2_range": 10540.0, "MAC2_rssi": -79.20758946, "MAC3_range": 0, "MAC3_rssi": -100, "MAC4_range": 7870.0, "MAC4_rssi": -75.79397536, "MAC5_range": 10350.0, "MAC5_rssi": -79.16729518, "MAC6_range": 13200.0, "MAC6_rssi": -79.04487056, "MAC7_range": 0, "MAC7_rssi": -100, "MAC8_range": 0, "MAC8_rssi": -100, "MAC9_range": 6590.0, "MAC9_rssi": -75.47865021, "MAC10_range": 3350.0, "MAC10_rssi": -75.2502558, "MAC11_range": 10960.0, "MAC11_rssi": -78.79379483, "MAC12_range": 0, "MAC12_rssi": -100, "MAC13_range": 0, "MAC13_rssi": -100, "MAC14_range": 0, "MAC14_rssi": -100}
{"timestamp": 1716263354, "x": 24.6130094637224, "y": 8.156697160883281, "MAC1_range": 0, "MAC1_rssi": -100, "MAC2_range": 13290.0, "MAC2_rssi": -79.34575382, "MAC3_range": 0, "MAC3_rssi": -100, "MAC4_range": 7860.0, "MAC4_rssi": -75.77886945, "MAC5_range": 10450.0, "MAC5_rssi": -79.09252992, "MAC6_range": 13050.0, "MAC6_rssi": -78.99057434, "MAC7_range": 0, "MAC7_rssi": -100, "MAC8_range": 0, "MAC8_rssi": -100, "MAC9_range": 6610.0, "MAC9_rssi": -75.28135801, "MAC10_range": 3320.0, "MAC10_rssi": -75.62754785, "MAC11_range": 10960.0, "MAC11_rssi": -78.90201427, "MAC12_range": 0, "MAC12_rssi": -100, "MAC13_range": 0, "MAC13_rssi": -100, "MAC14_range": 3180.0, "MAC14_rssi": -75.76622975}
{"timestamp": 1716263354, "x": 24.6130094637224, "y": 8.156697160883281, "MAC1_range": 0, "MAC1_rssi": -100, "MAC2_range": 13290.0, "MAC2_rssi": -79.34575382, "MAC3_range": 0, "MAC3_rssi": -100, "MAC4_range": 7860.0, "MAC4_rssi": -75.77886945, "MAC5_range": 10450.0, "MAC5_rssi": -79.09252992, "MAC6_range": 13050.0, "MAC6_rssi": -78.99057434, "MAC7_range": 0, "MAC7_rssi": -100, "MAC8_range": 0, "MAC8_rssi": -100, "MAC9_range": 6610.0, "MAC9_rssi": -75.28135801, "MAC10_range": 3350.0, "MAC10_rssi": -75.54864912, "MAC11_range": 10960.0, "MAC11_rssi": -78.90201427, "MAC12_range": 0, "MAC12_rssi": -100, "MAC13_range": 0, "MAC13_rssi": -100, "MAC14_range": 3180.0, "MAC14_rssi": -75.76622975}
{"timestamp": 1716263355, "x": 24.6130094637224, "y": 8.156697160883281, "MAC1_range": 0, "MAC1_rssi": -100, "MAC2_range": 13230.0, "MAC2_rssi": -78.9335335, "MAC3_range": 0, "MAC3_rssi": -100, "MAC4_range": 0, "MAC4_rssi": -100, "MAC5_range": 0, "MAC5_rssi": -100, "MAC6_range": 10940.0, "MAC6_rssi": -79.00050107, "MAC7_range": 0, "MAC7_rssi": -100, "MAC8_range": 0, "MAC8_rssi": -100, "MAC9_range": 0, "MAC9_rssi": -100, "MAC10_range": 3420.0, "MAC10_rssi": -75.53978522, "MAC11_range": 10970.0, "MAC11_rssi": -78.55602721, "MAC12_range": 0, "MAC12_rssi": -100, "MAC13_range": 0, "MAC13_rssi": -100, "MAC14_range": 0, "MAC14_rssi": -100}
{"timestamp": 1716263355, "x": 24.6130094637224, "y": 8.156697160883281, "MAC1_range": 0, "MAC1_rssi": -100, "MAC2_range": 13230.0, "MAC2_rssi": -78.9335335, "MAC3_range": 0, "MAC3_rssi": -100, "MAC4_range": 0, "MAC4_rssi": -100, "MAC5_range": 0, "MAC5_rssi": -100, "MAC6_range": 10940.0, "MAC6_rssi": -79.00050107, "MAC7_range": 0, "MAC7_rssi": -100, "MAC8_range": 0, "MAC8_rssi": -100, "MAC9_range": 0, "MAC9_rssi": -100, "MAC10_range": 3420.0, "MAC10_rssi": -75.53978522, "MAC11_range": 10970.0, "MAC11_rssi": -78.55602721, "MAC12_range": 0, "MAC12_rssi": -100, "MAC13_range": 0, "MAC13_rssi": -100, "MAC14_range": 0, "MAC14_rssi": -100}
{"timestamp": 1716263356, "x": 24.6130094637224, "y": 8.156697160883281, "MAC1_range": 0, "MAC1_rssi": -100, "MAC2_range": 10560.0, "MAC2_rssi": -79.17522794, "MAC3_range": 0, "MAC3_rssi": -100, "MAC4_range": 0, "MAC4_rssi": -100, "MAC5_range": 0, "MAC5_rssi": -100, "MAC6_range": 11240.0, "MAC6_rssi": -78.79005006, "MAC7_range": 0, "MAC7_rssi": -100, "MAC8_range": 0, "MAC8_rssi": -100, "MAC9_range": 0, "MAC9_rssi": -100, "MAC10_range": 3120.0, "MAC10_rssi": -75.45641727, "MAC11_range": 10980.0, "MAC11_rssi": -78.59648158, "MAC12_range": 0, "MAC12_rssi": -100, "MAC13_range": 0, "MAC13_rssi": -100, "MAC14_range": 0, "MAC14_rssi": -100}
{"timestamp": 1716263356, "x": 24.6130094637224, "y": 8.156697160883281, "MAC1_range": 0, "MAC1_rssi": -100, "MAC2_range": 12460.0, "MAC2_rssi": -79.39204412, "MAC3_range": 0, "MAC3_rssi": -100, "MAC4_range": 0, "MAC4_rssi": -100, "MAC5_range": 0, "MAC5_rssi": -100, "MAC6_range": 13060.0, "MAC6_rssi": -79.08286189, "MAC7_range": 0, "MAC7_rssi": -100, "MAC8_range": 0, "MAC8_rssi": -100, "MAC9_range": 0, "MAC9_rssi": -100, "MAC10_range": 3380.0, "MAC10_rssi": -75.45866612, "MAC11_range": 10980.0, "MAC11_rssi": -78.61336134, "MAC12_range": 0, "MAC12_rssi": -100, "MAC13_range": 0, "MAC13_rssi": -100, "MAC14_range": 0, "MAC14_rssi": -100}
{"timestamp": 1716263357, "x": 24.6130094637224, "y": 8.156697160883281, "MAC1_range": 0, "MAC1_rssi": -100, "MAC2_range": 13940.0, "MAC2_rssi": -79.40851532, "MAC3_range": 0, "MAC3_rssi": -100, "MAC4_range": 0, "MAC4_rssi": -100, "MAC5_range": 0, "MAC5_rssi": -100, "MAC6_range": 12660.0, "MAC6_rssi": -79.42352039, "MAC7_range": 0, "MAC7_rssi": -100, "MAC8_range": 0, "MAC8_rssi": -100, "MAC9_range": 0, "MAC9_rssi": -100, "MAC10_range": 3380.0, "MAC10_rssi": -75.43633154, "MAC11_range": 10940.0, "MAC11_rssi": -78.63073145, "MAC12_range": 0, "MAC12_rssi": -100, "MAC13_range": 0, "MAC13_rssi": -100, "MAC14_range": 0, "MAC14_rssi": -100}
{"timestamp": 1716263357, "x": 24.6130094637224, "y": 8.156697160883281, "MAC1_range": 0, "MAC1_rssi": -100, "MAC2_range": 13940.0, "MAC2_rssi": -79.40851532, "MAC3_range": 0, "MAC3_rssi": -100, "MAC4_range": 0, "MAC4_rssi": -100, "MAC5_range": 0, "MAC5_rssi": -100, "MAC6_range": 12660.0, "MAC6_rssi": -79.42352039, "MAC7_range": 0, "MAC7_rssi": -100, "MAC8_range": 0, "MAC8_rssi": -100, "MAC9_range": 0, "MAC9_rssi": -100, "MAC10_range": 3380.0, "MAC10_rssi": -75.43633154, "MAC11_range": 10940.0, "MAC11_rssi": -78.63073145, "MAC12_range": 0, "MAC12_rssi": -100, "MAC13_range": 0, "MAC13_rssi": -100, "MAC14_range": 0, "MAC14_rssi": -100}
{"timestamp": 1716263358, "x": 24.6130094637224, "y": 8.156697160883281, "MAC1_range": 0, "MAC1_rssi": -100, "MAC2_range": 13250.0, "MAC2_rssi": -79.42504924, "MAC3_range": 0, "MAC3_rssi": -100, "MAC4_range": 0, "MAC4_rssi": -100, "MAC5_range": 0, "MAC5_rssi": -100, "MAC6_range": 12690.0, "MAC6_rssi": -79.13618512, "MAC7_range": 0, "MAC7_rssi": -100, "MAC8_range": 0, "MAC8_rssi": -100, "MAC9_range": 0, "MAC9_rssi": -100, "MAC10_range": 3290.0, "MAC10_rssi": -75.58333963, "MAC11_range": 10980.0, "MAC11_rssi": -78.52049637, "MAC12_range": 0, "MAC12_rssi": -100, "MAC13_range": 0, "MAC13_rssi": -100, "MAC14_range": 0, "MAC14_rssi": -100}
{"timestamp": 1716263358, "x": 24.6130094637224, "y": 8.156697160883281, "MAC1_range": 0, "MAC1_rssi": -100, "MAC2_range": 10480.0, "MAC2_rssi": -78.80770075, "MAC3_range": 0, "MAC3_rssi": -100, "MAC4_range": 0, "MAC4_rssi": -100, "MAC5_range": 0, "MAC5_rssi": -100, "MAC6_range": 12580.0, "MAC6_rssi": -78.17916751, "MAC7_range": 0, "MAC7_rssi": -100, "MAC8_range": 0, "MAC8_rssi": -100, "MAC9_range": 0, "MAC9_rssi": -100, "MAC10_range": 3230.0, "MAC10_rssi": -75.90347891, "MAC11_range": 10980.0, "MAC11_rssi": -78.75103278, "MAC12_range": 0, "MAC12_rssi": -100, "MAC13_range": 0, "MAC13_rssi": -100, "MAC14_range": 0, "MAC14_rssi": -100}
{"timestamp": 1716263359, "x": 24.6130094637224, "y": 8.156697160883281, "MAC1_range": 0, "MAC1_rssi": -100, "MAC2_range": 10510.0, "MAC2_rssi": -78.96964112, "MAC3_range": 0, "MAC3_rssi": -100, "MAC4_range": 0, "MAC4_rssi": -100, "MAC5_range": 0, "MAC5_rssi": -100, "MAC6_range": 12830.0, "MAC6_rssi": -78.31439157, "MAC7_range": 0, "MAC7_rssi": -100, "MAC8_range": 0, "MAC8_rssi": -100, "MAC9_range": 0, "MAC9_rssi": -100, "MAC10_range": 3240.0, "MAC10_rssi": -75.77798898, "MAC11_range": 10970.0, "MAC11_rssi": -79.10080017, "MAC12_range": 0, "MAC12_rssi": -100, "MAC13_range": 0, "MAC13_rssi": -100, "MAC14_range": 0, "MAC14_rssi": -100}
{"timestamp": 1716263359, "x": 24.6130094637224, "y": 8.156697160883281, "MAC1_range": 0, "MAC1_rssi": -100, "MAC2_range": 12470.0, "MAC2_rssi": -79.13618512, "MAC3_range": 0, "MAC3_rssi": -100, "MAC4_range": 0, "MAC4_rssi": -100, "MAC5_range": 0, "MAC5_rssi": -100, "MAC6_range": 12830.0, "MAC6_rssi": -78.31439157, "MAC7_range": 0, "MAC7_rssi": -100, "MAC8_range": 0, "MAC8_rssi": -100, "MAC9_range": 0, "MAC9_rssi": -100, "MAC10_range": 3340.0, "MAC10_rssi": -76.02640607, "MAC11_range": 10950.0, "MAC11_rssi": -78.65883984, "MAC12_range": 0, "MAC12_rssi": -100, "MAC13_range": 0, "MAC13_rssi": -100, "MAC14_range": 0, "MAC14_rssi": -100}
{"timestamp": 1716263360, "x": 24.6130094637224, "y": 8.156697160883281, "MAC1_range": 0, "MAC1_rssi": -100, "MAC2_range": 13360.0, "MAC2_rssi": -79.48458123, "MAC3_range": 0, "MAC3_rssi": -100, "MAC4_range": 7870.0, "MAC4_rssi": -75.73920558, "MAC5_range": 10610.0, "MAC5_rssi": -79.38067746, "MAC6_range": 12840.0, "MAC6_rssi": -78.49594066, "MAC7_range": 0, "MAC7_rssi": -100, "MAC8_range": 0, "MAC8_rssi": -100, "MAC9_range": 6620.0, "MAC9_rssi": -75.29433406, "MAC10_range": 3360.0, "MAC10_rssi": -75.56381177, "MAC11_range": 11050.0, "MAC11_rssi": -78.5832348, "MAC12_range": 0, "MAC12_rssi": -100, "MAC13_range": 0, "MAC13_rssi": -100, "MAC14_range": 3270.0, "MAC14_rssi": -75.89578307}
{"timestamp": 1716263360, "x": 24.6130094637224, "y": 8.156697160883281, "MAC1_range": 0, "MAC1_rssi": -100, "MAC2_range": 13290.0, "MAC2_rssi": -79.11715066, "MAC3_range": 0, "MAC3_rssi": -100, "MAC4_range": 7870.0, "MAC4_rssi": -75.73920558, "MAC5_range": 10610.0, "MAC5_rssi": -79.38067746, "MAC6_range": 11360.0, "MAC6_rssi": -79.16369416, "MAC7_range": 0, "MAC7_rssi": -100, "MAC8_range": 0, "MAC8_rssi": -100, "MAC9_range": 6620.0, "MAC9_rssi": -75.29433406, "MAC10_range": 3280.0, "MAC10_rssi": -75.45733712, "MAC11_range": 11050.0, "MAC11_rssi": -78.5832348, "MAC12_range": 0, "MAC12_rssi": -100, "MAC13_range": 0, "MAC13_rssi": -100, "MAC14_range": 3270.0, "MAC14_rssi": -75.89578307}
{"timestamp": 1716263361, "x": 24.6130094637224, "y": 8.156697160883281, "MAC1_range": 0, "MAC1_rssi": -100, "MAC2_range": 11960.0, "MAC2_rssi": -79.64833633, "MAC3_range": 0, "MAC3_rssi": -100, "MAC4_range": 0, "MAC4_rssi": -100, "MAC5_range": 0, "MAC5_rssi": -100, "MAC6_range": 11250.0, "MAC6_rssi": -79.32528232, "MAC7_range": 0, "MAC7_rssi": -100, "MAC8_range": 0, "MAC8_rssi": -100, "MAC9_range": 0, "MAC9_rssi": -100, "MAC10_range": 3340.0, "MAC10_rssi": -75.32218621, "MAC11_range": 11010.0, "MAC11_rssi": -78.53168527, "MAC12_range": 0, "MAC12_rssi": -100, "MAC13_range": 0, "MAC13_rssi": -100, "MAC14_range": 0, "MAC14_rssi": -100}
{"timestamp": 1716263361, "x": 24.6130094637224, "y": 8.156697160883281, "MAC1_range": 0, "MAC1_rssi": -100, "MAC2_range": 11950.0, "MAC2_rssi": -79.79485658, "MAC3_range": 0, "MAC3_rssi": -100, "MAC4_range": 0, "MAC4_rssi": -100, "MAC5_range": 0, "MAC5_rssi": -100, "MAC6_range": 9220.0, "MAC6_rssi": -79.62799338, "MAC7_range": 0, "MAC7_rssi": -100, "MAC8_range": 0, "MAC8_rssi": -100, "MAC9_range": 0, "MAC9_rssi": -100, "MAC10_range": 3480.0, "MAC10_rssi": -75.39905803, "MAC11_range": 10930.0, "MAC11_rssi": -78.59648158, "MAC12_range": 0, "MAC12_rssi": -100, "MAC13_range": 0, "MAC13_rssi": -100, "MAC14_range": 0, "MAC14_rssi": -100}
{"timestamp": 1716263362, "x": 24.6130094637224, "y": 8.156697160883281, "MAC1_range": 0, "MAC1_rssi": -100, "MAC2_range": 11860.0, "MAC2_rssi": -79.90075648, "MAC3_range": 0, "MAC3_rssi": -100, "MAC4_range": 0, "MAC4_rssi": -100, "MAC5_range": 0, "MAC5_rssi": -100, "MAC6_range": 9080.0, "MAC6_rssi": -80.14192267, "MAC7_range": 0, "MAC7_rssi": -100, "MAC8_range": 0, "MAC8_rssi": -100, "MAC9_range": 0, "MAC9_rssi": -100, "MAC10_range": 3380.0, "MAC10_rssi": -75.41198648, "MAC11_range": 11020.0, "MAC11_rssi": -78.77290944, "MAC12_range": 0, "MAC12_rssi": -100, "MAC13_range": 0, "MAC13_rssi": -100, "MAC14_range": 0, "MAC14_rssi": -100}
{"timestamp": 1716263362, "x": 24.6130094637224, "y": 8.156697160883281, "MAC1_range": 0, "MAC1_rssi": -100, "MAC2_range": 10530.0, "MAC2_rssi": -79.48174009, "MAC3_range": 0, "MAC3_rssi": -100, "MAC4_range": 0, "MAC4_rssi": -100, "MAC5_range": 0, "MAC5_rssi": -100, "MAC6_range": 9080.0, "MAC6_rssi": -80.14192267, "MAC7_range": 0, "MAC7_rssi": -100, "MAC8_range": 0, "MAC8_rssi": -100, "MAC9_range": 0, "MAC9_rssi": -100, "MAC10_range": 3420.0, "MAC10_rssi": -75.65762879, "MAC11_range": 11020.0, "MAC11_rssi": -79.70260191, "MAC12_range": 0, "MAC12_rssi": -100, "MAC13_range": 0, "MAC13_rssi": -100, "MAC14_range": 0, "MAC14_rssi": -100}
{"timestamp": 1716263363, "x": 24.6130094637224, "y": 8.156697160883281, "MAC1_range": 0, "MAC1_rssi": -100, "MAC2_range": 12320.0, "MAC2_rssi": -79.67389976, "MAC3_range": 0, "MAC3_rssi": -100, "MAC4_range": 0, "MAC4_rssi": -100, "MAC5_range": 0, "MAC5_rssi": -100, "MAC6_range": 10310.0, "MAC6_rssi": -80.4900698, "MAC7_range": 0, "MAC7_rssi": -100, "MAC8_range": 0, "MAC8_rssi": -100, "MAC9_range": 0, "MAC9_rssi": -100, "MAC10_range": 3170.0, "MAC10_rssi": -75.61120821, "MAC11_range": 11820.0, "MAC11_rssi": -80.23059446, "MAC12_range": 0, "MAC12_rssi": -100, "MAC13_range": 0, "MAC13_rssi": -100, "MAC14_range": 0, "MAC14_rssi": -100}
{"timestamp": 1716263363, "x": 24.6130094637224, "y": 8.156697160883281, "MAC1_range": 0, "MAC1_rssi": -100, "MAC2_range": 12610.0, "MAC2_rssi": -80.13471446, "MAC3_range": 0, "MAC3_rssi": -100, "MAC4_range": 0, "MAC4_rssi": -100, "MAC5_range": 0, "MAC5_rssi": -100, "MAC6_range": 9870.0, "MAC6_rssi": -79.96146191, "MAC7_range": 0, "MAC7_rssi": -100, "MAC8_range": 0, "MAC8_rssi": -100, "MAC9_range": 0, "MAC9_rssi": -100, "MAC10_range": 3320.0, "MAC10_rssi": -75.68899756, "MAC11_range": 11700.0, "MAC11_rssi": -80.61830852, "MAC12_range": 0, "MAC12_rssi": -100, "MAC13_range": 0, "MAC13_rssi": -100, "MAC14_range": 0, "MAC14_rssi": -100}
{"timestamp": 1716263364, "x": 24.6130094637224, "y": 8.156697160883281, "MAC1_range": 0, "MAC1_rssi": -100, "MAC2_range": 10440.0, "MAC2_rssi": -80.40333377, "MAC3_range": 0, "MAC3_rssi": -100, "MAC4_range": 0, "MAC4_rssi": -100, "MAC5_range": 0, "MAC5_rssi": -100, "MAC6_range": 9380.0, "MAC6_rssi": -79.32852138, "MAC7_range": 0, "MAC7_rssi": -100, "MAC8_range": 0, "MAC8_rssi": -100, "MAC9_range": 0, "MAC9_rssi": -100, "MAC10_range": 3400.0, "MAC10_rssi": -75.5047161, "MAC11_range": 11170.0, "MAC11_rssi": -80.67605097, "MAC12_range": 0, "MAC12_rssi": -100, "MAC13_range": 0, "MAC13_rssi": -100, "MAC14_range": 0, "MAC14_rssi": -100}
{"timestamp": 1716263364, "x": 24.6130094637224, "y": 8.156697160883281, "MAC1_range": 0, "MAC1_rssi": -100, "MAC2_range": 12000.0, "MAC2_rssi": -79.07415553, "MAC3_range": 0, "MAC3_rssi": -100, "MAC4_range": 0, "MAC4_rssi": -100, "MAC5_range": 0, "MAC5_rssi": -100, "MAC6_range": 9380.0, "MAC6_rssi": -79.32852138, "MAC7_range": 0, "MAC7_rssi": -100, "MAC8_range": 0, "MAC8_rssi": -100, "MAC9_range": 0, "MAC9_rssi": -100, "MAC10_range": 6580.0, "MAC10_rssi": -75.52491371, "MAC11_range": 12620.0, "MAC11_rssi": -78.95223542, "MAC12_range": 0, "MAC12_rssi": -100, "MAC13_range": 0, "MAC13_rssi": -100, "MAC14_range": 0, "MAC14_rssi": -100}
{"timestamp": 1716263365, "x": 24.6130094637224, "y": 8.156697160883281, "MAC1_range": 0, "MAC1_rssi": -100, "MAC2_range": 10130.0, "MAC2_rssi": -80.27530867, "MAC3_range": 0, "MAC3_rssi": -100, "MAC4_range": 0, "MAC4_rssi": -100, "MAC5_range": 0, "MAC5_rssi": -100, "MAC6_range": 10020.0, "MAC6_rssi": -79.97821891, "MAC7_range": 0, "MAC7_rssi": -100, "MAC8_range": 0, "MAC8_rssi": -100, "MAC9_range": 0, "MAC9_rssi": -100, "MAC10_range": 3430.0, "MAC10_rssi": -75.68684177, "MAC11_range": 14440.0, "MAC11_rssi": -78.80858517, "MAC12_range": 0, "MAC12_rssi": -100, "MAC13_range": 0, "MAC13_rssi": -100, "MAC14_range": 0, "MAC14_rssi": -100}
{"timestamp": 1716263365, "x": 24.6130094637224, "y": 8.156697160883281, "MAC1_range": 0, "MAC1_rssi": -100, "MAC2_range": 10130.0, "MAC2_rssi": -80.27530867, "MAC3_range": 0, "MAC3_rssi": -100, "MAC4_range": 0, "MAC4_rssi": -100, "MAC5_range": 0, "MAC5_rssi": -100, "MAC6_range": 9770.0, "MAC6_rssi": -80.32612945, "MAC7_range": 0, "MAC7_rssi": -100, "MAC8_range": 0, "MAC8_rssi": -100, "MAC9_range": 0, "MAC9_rssi": -100, "MAC10_range": 3430.0, "MAC10_rssi": -75.68684177, "MAC11_range": 12590.0, "MAC11_rssi": -80.7591031, "MAC12_range": 0, "MAC12_rssi": -100, "MAC13_range": 0, "MAC13_rssi": -100, "MAC14_range": 0, "MAC14_rssi": -100}
{"timestamp": 1716263366, "x": 24.6130094637224, "y": 8.156697160883281, "MAC1_range": 0, "MAC1_rssi": -100, "MAC2_range": 12100.0, "MAC2_rssi": -79.38168663, "MAC3_range": 0, "MAC3_rssi": -100, "MAC4_range": 0, "MAC4_rssi": -100, "MAC5_range": 0, "MAC5_rssi": -100, "MAC6_range": 10030.0, "MAC6_rssi": -80.19819568, "MAC7_range": 0, "MAC7_rssi": -100, "MAC8_range": 0, "MAC8_rssi": -100, "MAC9_range": 0, "MAC9_rssi": -100, "MAC10_range": 4970.0, "MAC10_rssi": -75.5357243, "MAC11_range": 14990.0, "MAC11_rssi": -79.19911353, "MAC12_range": 0, "MAC12_rssi": -100, "MAC13_range": 0, "MAC13_rssi": -100, "MAC14_range": 0, "MAC14_rssi": -100}
{"timestamp": 1716263366, "x": 24.6130094637224, "y": 8.156697160883281, "MAC1_range": 0, "MAC1_rssi": -100, "MAC2_range": 11400.0, "MAC2_rssi": -79.81153885, "MAC3_range": 0, "MAC3_rssi": -100, "MAC4_range": 0, "MAC4_rssi": -100, "MAC5_range": 0, "MAC5_rssi": -100, "MAC6_range": 10690.0, "MAC6_rssi": -80.08607273, "MAC7_range": 0, "MAC7_rssi": -100, "MAC8_range": 0, "MAC8_rssi": -100, "MAC9_range": 0, "MAC9_rssi": -100, "MAC10_range": 5060.0, "MAC10_rssi": -75.51817073, "MAC11_range": 15080.0, "MAC11_rssi": -79.70912694, "MAC12_range": 0, "MAC12_rssi": -100, "MAC13_range": 0, "MAC13_rssi": -100, "MAC14_range": 0, "MAC14_rssi": -100}
{"timestamp": 1716263367, "x": 24.6130094637224, "y": 8.156697160883281, "MAC1_range": 0, "MAC1_rssi": -100, "MAC2_range": 10130.0, "MAC2_rssi": -80.43248223, "MAC3_range": 0, "MAC3_rssi": -100, "MAC4_range": 0, "MAC4_rssi": -100, "MAC5_range": 0, "MAC5_rssi": -100, "MAC6_range": 12530.0, "MAC6_rssi": -79.94505659, "MAC7_range": 0, "MAC7_rssi": -100, "MAC8_range": 0, "MAC8_rssi": -100, "MAC9_range": 0, "MAC9_rssi": -100, "MAC10_range": 5920.0, "MAC10_rssi": -75.71571015, "MAC11_range": 15100.0, "MAC11_rssi": -80.20612021, "MAC12_range": 0, "MAC12_rssi": -100, "MAC13_range": 0, "MAC13_rssi": -100, "MAC14_range": 0, "MAC14_rssi": -100}
{"timestamp": 1716263367, "x": 24.6130094637224, "y": 8.156697160883281, "MAC1_range": 0, "MAC1_rssi": -100, "MAC2_range": 11430.0, "MAC2_rssi": -80.01981191, "MAC3_range": 0, "MAC3_rssi": -100, "MAC4_range": 0, "MAC4_rssi": -100, "MAC5_range": 0, "MAC5_rssi": -100, "MAC6_range": 12530.0, "MAC6_rssi": -79.94505659, "MAC7_range": 0, "MAC7_rssi": -100, "MAC8_range": 0, "MAC8_rssi": -100, "MAC9_range": 0, "MAC9_rssi": -100, "MAC10_range": 5920.0, "MAC10_rssi": -75.71571015, "MAC11_range": 12170.0, "MAC11_rssi": -80.18846222, "MAC12_range": 0, "MAC12_rssi": -100, "MAC13_range": 0, "MAC13_rssi": -100, "MAC14_range": 0, "MAC14_rssi": -100}
{"timestamp": 1716263368, "x": 24.6130094637224, "y": 8.156697160883281, "MAC1_range": 0, "MAC1_rssi": -100, "MAC2_range": 0, "MAC2_rssi": -100, "MAC3_range": 0, "MAC3_rssi": -100, "MAC4_range": 7230.0, "MAC4_rssi": -75.20739234, "MAC5_range": 10140.0, "MAC5_rssi": -78.85192053, "MAC6_range": 0, "MAC6_rssi": -100, "MAC7_range": 0, "MAC7_rssi": -100, "MAC8_range": 0, "MAC8_rssi": -100, "MAC9_range": 6080.0, "MAC9_rssi": -76.04684625, "MAC10_range": 4750.0, "MAC10_rssi": -75.90291258, "MAC11_range": 0, "MAC11_rssi": -100, "MAC12_range": 0, "MAC12_rssi": -100, "MAC13_range": 0, "MAC13_rssi": -100, "MAC14_range": 2980.0, "MAC14_rssi": -77.04413597}
{"timestamp": 1716263368, "x": 24.6130094637224, "y": 8.156697160883281, "MAC1_range": 0, "MAC1_rssi": -100, "MAC2_range": 0, "MAC2_rssi": -100, "MAC3_range": 0, "MAC3_rssi": -100, "MAC4_range": 7160.0, "MAC4_rssi": -75.03429475, "MAC5_range": 10050.0, "MAC5_rssi": -79.37361986, "MAC6_range": 0, "MAC6_rssi": -100, "MAC7_range": 0, "MAC7_rssi": -100, "MAC8_range": 0, "MAC8_rssi": -100, "MAC9_range": 6060.0, "MAC9_rssi": -76.52143048, "MAC10_range": 5990.0, "MAC10_rssi": -75.91550264, "MAC11_range": 0, "MAC11_rssi": -100, "MAC12_range": 0, "MAC12_rssi": -100, "MAC13_range": 0, "MAC13_rssi": -100, "MAC14_range": 3000.0, "MAC14_rssi": -77.00732057}
{"timestamp": 1716263369, "x": 24.6130094637224, "y": 8.156697160883281, "MAC1_range": 0, "MAC1_rssi": -100, "MAC2_range": 0, "MAC2_rssi": -100, "MAC3_range": 0, "MAC3_rssi": -100, "MAC4_range": 7160.0, "MAC4_rssi": -75.09988303, "MAC5_range": 8530.0, "MAC5_rssi": -79.15290899, "MAC6_range": 0, "MAC6_rssi": -100, "MAC7_range": 0, "MAC7_rssi": -100, "MAC8_range": 0, "MAC8_rssi": -100, "MAC9_range": 6040.0, "MAC9_rssi": -76.49214551, "MAC10_range": 4720.0, "MAC10_rssi": -75.5628691, "MAC11_range": 0, "MAC11_rssi": -100, "MAC12_range": 0, "MAC12_rssi": -100, "MAC13_range": 0, "MAC13_rssi": -100, "MAC14_range": 2940.0, "MAC14_rssi": -76.56804102}
{"timestamp": 1716263369, "x": 24.6130094637224, "y": 8.156697160883281, "MAC1_range": 0, "MAC1_rssi": -100, "MAC2_range": 0, "MAC2_rssi": -100, "MAC3_range": 0, "MAC3_rssi": -100, "MAC4_range": 7210.0, "MAC4_rssi": -75.56737483, "MAC5_range": 8710.0, "MAC5_rssi": -79.63895603, "MAC6_range": 0, "MAC6_rssi": -100, "MAC7_range": 0, "MAC7_rssi": -100, "MAC8_range": 0, "MAC8_rssi": -100, "MAC9_range": 6030.0, "MAC9_rssi": -76.85533895, "MAC10_range": 6710.0, "MAC10_rssi": -75.45243353, "MAC11_range": 0, "MAC11_rssi": -100, "MAC12_range": 0, "MAC12_rssi": -100, "MAC13_range": 0, "MAC13_rssi": -100, "MAC14_range": 2990.0, "MAC14_rssi": -76.62076552}
{"timestamp": 1716263370, "x": 24.6130094637224, "y": 8.156697160883281, "MAC1_range": 0, "MAC1_rssi": -100, "MAC2_range": 0, "MAC2_rssi": -100, "MAC3_range": 0, "MAC3_rssi": -100, "MAC4_range": 7190.0, "MAC4_rssi": -75.64096253, "MAC5_range": 8500.0, "MAC5_rssi": -79.5386575, "MAC6_range": 0, "MAC6_rssi": -100, "MAC7_range": 0, "MAC7_rssi": -100, "MAC8_range": 0, "MAC8_rssi": -100, "MAC9_range": 6070.0, "MAC9_rssi": -76.47079467, "MAC10_range": 5950.0, "MAC10_rssi": -75.69482355, "MAC11_range": 0, "MAC11_rssi": -100, "MAC12_range": 0, "MAC12_rssi": -100, "MAC13_range": 0, "MAC13_rssi": -100, "MAC14_range": 2950.0, "MAC14_rssi": -76.45945034}
{"timestamp": 1716263370, "x": 24.6130094637224, "y": 8.156697160883281, "MAC1_range": 0, "MAC1_rssi": -100, "MAC2_range": 0, "MAC2_rssi": -100, "MAC3_range": 0, "MAC3_rssi": -100, "MAC4_range": 7210.0, "MAC4_rssi": -75.73920558, "MAC5_range": 9450.0, "MAC5_rssi": -79.80931084, "MAC6_range": 0, "MAC6_rssi": -100, "MAC7_range": 0, "MAC7_rssi": -100, "MAC8_range": 0, "MAC8_rssi": -100, "MAC9_range": 6070.0, "MAC9_rssi": -76.47079467, "MAC10_range": 5950.0, "MAC10_rssi": -75.69482355, "MAC11_range": 0, "MAC11_rssi": -100, "MAC12_range": 0, "MAC12_rssi": -100, "MAC13_range": 0, "MAC13_rssi": -100, "MAC14_range": 2970.0, "MAC14_rssi": -76.80458305}
